kiwi/__init__.py
KiwiCoder-0.2.3.4.dist-info/LICENSE
KiwiCoder-0.2.3.4.dist-info/METADATA
KiwiCoder-0.2.3.4.dist-info/WHEEL
KiwiCoder-0.2.3.4.dist-info/top_level.txt
KiwiCoder-0.2.3.4.dist-info/RECORD
